aws_s3_cli/__init__.py
aws_s3_cli/aws_s3_cli.py
aws_s3_cli-0.0.7.dist-info/licenses/LICENSE
aws_s3_cli-0.0.7.dist-info/METADATA
aws_s3_cli-0.0.7.dist-info/WHEEL
aws_s3_cli-0.0.7.dist-info/top_level.txt
aws_s3_cli-0.0.7.dist-info/RECORD
